{
	"children" : { 
		"Home" : {
			"icon" : "",
			"path" : "/",
			"children" : {}
		}, 
		"Blogs" : {
			"icon" : "",
			"path" : "/blogs",
			"children" : {}
		}, 
		"Media" : {
			"icon" : "",
			"path" : "/media",
			"children" : {
				"Music" : {
					"thumb" : "",
					"path" : "/music"
				},
				"Movie" : {
					"thumb" : "",
					"path" : "/movie"
				},
				"TV" : {
					"thumb" : "",
					"path" : "/tv"
				}
			}
		}, 
		"About Me" : {
			"icon" : "",
			"path" : "/about",
			"children" : {}
		} 
	}
}